{
	"format_version": "1.14",
	"minecraft:npc_dialogue":
	{
		"scenes":
		[
			{
				"scene_tag": "toggle_module_pag1",
        "npc_name": { "rawtext": [ { "text": "§¶§bUnity AntiCheat §7[§2v2.3§7]" } ] },
				"text": { "rawtext": [ { "text": "§¶§c§lUAC ► §5GUI TOGGLE MENU PAGE 1\n\n§¶§l§0ACM ► Anti-CBE \n§¶§l§0AFM ► Anti-Fly \n§¶§l§0BBM ► Bottom Bedrock \n§¶§l§0DAM ► Disable Enchanted Armor \n§¶§l§0SSM ► Fake Staff Protection" } ] },
				"buttons": [
					{
						"name": { "rawtext": [ { "text": "§l§2ACM" } ] },
						"commands": [
							"/execute @s[tag=staffstatus] ~~~ dialogue open @s @s toggle_module_pag1",
							"/execute @s[tag=staffstatus] ~~~ function toggle/anticbe"
						]
					},
					{
						"name": { "rawtext": [ { "text": "§l§2AFM" } ] },
						"commands": [
              "/execute @s[tag=staffstatus] ~~~ dialogue open @s @s toggle_module_pag1",
              "/execute @s[tag=staffstatus] ~~~ function toggle/antifly"
						]
					},
					{
						"name": { "rawtext": [ { "text": "§l§2BBM" } ] },
						"commands": [
							"/execute @s[tag=staffstatus] ~~~ dialogue open @s @s toggle_module_pag1",
							"/execute @s[tag=staffstatus] ~~~ function toggle/bottombedrock"
						]
					},
					{
						"name": { "rawtext": [ { "text": "§l§2DAM" } ] },
						"commands": [
							"/execute @s[tag=staffstatus] ~~~ dialogue open @s @s toggle_module_pag1",
							"/execute @s[tag=staffstatus] ~~~ function toggle/enchanted_armor_disable"
						]
					},
					{
						"name": { "rawtext": [ { "text": "§l§2SSM" } ] },
						"commands": [
							"/execute @s[tag=staffstatus] ~~~ dialogue open @s @s toggle_module_pag1",
							"/execute @s[tag=staffstatus] ~~~ function toggle/fakestaffprotection"
						]
					},
					{
						"name": { "rawtext": [ { "text": "§l§9Page 2" } ] },
						"commands": [
							"/execute @s[tag=staffstatus] ~~~ dialogue open @s @s toggle_module_pag2"
						]
					}
				],
				"on_close_commands": [
                    " "
				]
			}
		]
	}
}
